tappd_client.py
tappd_client-0.1.3.dist-info/METADATA
tappd_client-0.1.3.dist-info/WHEEL
tappd_client-0.1.3.dist-info/RECORD
