Metadata-Version: 2.3
Name: tappd-client
Version: 0.1.3
Summary: Python client for Tappd in DStack CVM
Author-email: Kevin Wang <wy721@qq.com>
License: MIT
Keywords: dstack,tappd
Classifier: Development Status :: 3 - Alpha
Classifier: Intended Audience :: Developers
Classifier: License :: OSI Approved :: MIT License
Classifier: Programming Language :: Python :: 3
Classifier: Programming Language :: Python :: 3.7
Requires-Python: >=3.7
Requires-Dist: requests-unixsocket2>=0.4.2
